pylint/__init__.py
pylint/__main__.py
pylint/__pkginfo__.py
pylint/constants.py
pylint/exceptions.py
pylint/graph.py
pylint/interfaces.py
pylint/py.typed
pylint/typing.py
pylint/checkers/__init__.py
pylint/checkers/async_checker.py
pylint/checkers/bad_chained_comparison.py
pylint/checkers/base_checker.py
pylint/checkers/clear_lru_cache.py
pylint/checkers/dataclass_checker.py
pylint/checkers/deprecated.py
pylint/checkers/design_analysis.py
pylint/checkers/dunder_methods.py
pylint/checkers/ellipsis_checker.py
pylint/checkers/exceptions.py
pylint/checkers/format.py
pylint/checkers/imports.py
pylint/checkers/lambda_expressions.py
pylint/checkers/logging.py
pylint/checkers/match_statements_checker.py
pylint/checkers/method_args.py
pylint/checkers/misc.py
pylint/checkers/modified_iterating_checker.py
pylint/checkers/nested_min_max.py
pylint/checkers/newstyle.py
pylint/checkers/non_ascii_names.py
pylint/checkers/raw_metrics.py
pylint/checkers/spelling.py
pylint/checkers/stdlib.py
pylint/checkers/strings.py
pylint/checkers/symilar.py
pylint/checkers/threading_checker.py
pylint/checkers/typecheck.py
pylint/checkers/unicode.py
pylint/checkers/unsupported_version.py
pylint/checkers/utils.py
pylint/checkers/variables.py
pylint/checkers/base/__init__.py
pylint/checkers/base/basic_checker.py
pylint/checkers/base/basic_error_checker.py
pylint/checkers/base/comparison_checker.py
pylint/checkers/base/docstring_checker.py
pylint/checkers/base/function_checker.py
pylint/checkers/base/pass_checker.py
pylint/checkers/base/name_checker/__init__.py
pylint/checkers/base/name_checker/checker.py
pylint/checkers/base/name_checker/naming_style.py
pylint/checkers/classes/__init__.py
pylint/checkers/classes/class_checker.py
pylint/checkers/classes/special_methods_checker.py
pylint/checkers/refactoring/__init__.py
pylint/checkers/refactoring/implicit_booleaness_checker.py
pylint/checkers/refactoring/not_checker.py
pylint/checkers/refactoring/recommendation_checker.py
pylint-4.0.0.dist-info/licenses/CONTRIBUTORS.txt
pylint-4.0.0.dist-info/licenses/LICENSE
pylint-4.0.0.dist-info/METADATA
pylint-4.0.0.dist-info/WHEEL
pylint-4.0.0.dist-info/entry_points.txt
pylint-4.0.0.dist-info/top_level.txt
pylint-4.0.0.dist-info/RECORD
