Metadata-Version: 2.4
Name: pylint
Version: 4.0.0
Summary: python code static checker
Author-email: Python Code Quality Authority <code-quality@python.org>
License-Expression: GPL-2.0-or-later
Project-URL: Bug Tracker, https://github.com/pylint-dev/pylint/issues
Project-URL: Discord Server, https://discord.com/invite/Egy6P8AMB5
Project-URL: Docs: Contributor Guide, https://pylint.readthedocs.io/en/latest/development_guide/contributor_guide/index.html
Project-URL: Docs: User Guide, https://pylint.readthedocs.io/en/latest/
Project-URL: homepage, https://github.com/pylint-dev/pylint
Project-URL: Source Code, https://github.com/pylint-dev/pylint
Project-URL: What's New, https://pylint.readthedocs.io/en/latest/whatsnew/3/
Keywords: lint,linter,python,static code analysis
Classifier: Development Status :: 6 - Mature
Classifier: Environment :: Console
Classifier: Intended Audience :: Developers
Classifier: Operating System :: OS Independent
Classifier: Programming Language :: Python
Classifier: Programming Language :: Python :: 3 :: Only
Classifier: Programming Language :: Python :: 3.10
Classifier: Programming Language :: Python :: 3.11
Classifier: Programming Language :: Python :: 3.12
Classifier: Programming Language :: Python :: 3.13
Classifier: Programming Language :: Python :: 3.14
Classifier: Programming Language :: Python :: Implementation :: CPython
Classifier: Programming Language :: Python :: Implementation :: PyPy
Classifier: Topic :: Software Development :: Debuggers
Classifier: Topic :: Software Development :: Quality Assurance
Classifier: Topic :: Software Development :: Testing
Classifier: Typing :: Typed
Requires-Python: >=3.10.0
License-File: LICENSE
License-File: CONTRIBUTORS.txt
Requires-Dist: astroid<=4.1.dev0,>=4.0.1
Requires-Dist: colorama>=0.4.5; sys_platform == "win32"
Requires-Dist: dill>=0.2; python_version < "3.11"
Requires-Dist: dill>=0.3.6; python_version >= "3.11"
Requires-Dist: dill>=0.3.7; python_version >= "3.12"
Requires-Dist: isort!=5.13,<8,>=5
Requires-Dist: mccabe<0.8,>=0.6
Requires-Dist: platformdirs>=2.2
Requires-Dist: tomli>=1.1; python_version < "3.11"
Requires-Dist: tomlkit>=0.10.1
Requires-Dist: typing-extensions>=3.10; python_version < "3.10"
Provides-Extra: spelling
Requires-Dist: pyenchant~=3.2; extra == "spelling"
Provides-Extra: testutils
Requires-Dist: gitpython>3; extra == "testutils"
Dynamic: license-file
